MANIFEST.in
README.md
requirements.txt
setup.py
ifacetools/__init__.py
ifacetools.egg-info/PKG-INFO
ifacetools.egg-info/SOURCES.txt
ifacetools.egg-info/dependency_links.txt
ifacetools.egg-info/top_level.txt
ifacetools/fbtest/__init__.py
ifacetools/fbtest/numpv.py
ifacetools/fbtest/school.py
ifacetools/fbtest/use.py
ifacetools/fbtest/user.py
ifacetools/fbtest/userfc.py
ifacetools/httputil/HTTPUtil.py
ifacetools/httputil/__init__.py
ifacetools/jsonutil/JSONUtil.py
ifacetools/jsonutil/__init__.py
ifacetools/randomutil/__init__.py
ifacetools/randomutil/constant.py
ifacetools/randomutil/identity.py
ifacetools/randomutil/myrandom.py
ifacetools/redisutil/RedisUtil.py
ifacetools/redisutil/__init__.py
ifacetools/time/TimeUtil.py
ifacetools/time/__init__.py
ifacetools/util/__init__.py
ifacetools/util/hutil.py