Metadata-Version: 2.1
Name: ifacetools
Version: 0.1.5
Summary: A lib created by Vincent for Interface automation test
Home-page: https://github.com/huangchunhao/ifacetools
Author: Vincent
Author-email: Vincent@163.com
Maintainer: Vincent
Maintainer-email: Vincent@163.com
License: BSD License
Platform: all
Classifier: Development Status :: 4 - Beta
Classifier: Operating System :: OS Independent
Classifier: Intended Audience :: Developers
Classifier: License :: OSI Approved :: BSD License
Classifier: Programming Language :: Python
Classifier: Programming Language :: Python :: Implementation
Classifier: Programming Language :: Python :: 2
Classifier: Programming Language :: Python :: 2.7
Classifier: Programming Language :: Python :: 3
Classifier: Programming Language :: Python :: 3.4
Classifier: Programming Language :: Python :: 3.5
Classifier: Programming Language :: Python :: 3.6
Classifier: Topic :: Software Development :: Libraries
